setup.py
cli/__init__.py
cli/api.py
cli/auth.py
cli/langs.py
cli/main.py
cli/oplevelse.py
cli/stats.py
cli/tasks.py
oplevelse.egg-info/PKG-INFO
oplevelse.egg-info/SOURCES.txt
oplevelse.egg-info/dependency_links.txt
oplevelse.egg-info/entry_points.txt
oplevelse.egg-info/requires.txt
oplevelse.egg-info/top_level.txt