Metadata-Version: 1.0
Name: oplevelse
Version: 0.1.1
Summary: The Oplevelse CLI
Home-page: https://github.com/oplevelse/oplevelse-cli
Author: Platon Korzh
Author-email: platon@korzh.io
License: UNKNOWN
Platform: UNKNOWN
